statbank/__init__.py
statbank/api_exceptions.py
statbank/api_types.py
statbank/auth.py
statbank/client.py
statbank/get_apidata.py
statbank/globals.py
statbank/py.typed
statbank/response_to_pandas.py
statbank/statbank_logger.py
statbank/transfer.py
statbank/uttrekk.py
statbank/uttrekk_validations.py
dapla_statbank_client-1.3.5.dist-info/LICENSE
dapla_statbank_client-1.3.5.dist-info/METADATA
dapla_statbank_client-1.3.5.dist-info/WHEEL
dapla_statbank_client-1.3.5.dist-info/entry_points.txt
dapla_statbank_client-1.3.5.dist-info/RECORD
