Metadata-Version: 2.3
Name: dapla-statbank-client
Version: 1.3.5
Summary: Handles data transfer Statbank <-> Dapla for Statistics Norway
License: MIT
Author: Statistics Norway
Requires-Python: >=3.10,<4
Classifier: Development Status :: 5 - Production/Stable
Classifier: License :: OSI Approved :: MIT License
Classifier: Programming Language :: Python :: 3
Classifier: Programming Language :: Python :: 3.10
Classifier: Programming Language :: Python :: 3.11
Classifier: Programming Language :: Python :: 3.12
Classifier: Programming Language :: Python :: 3.13
Requires-Dist: IPython (>=8.11.0)
Requires-Dist: colorama (>=0.4.6)
Requires-Dist: dapla-auth-client (>=1.0.1)
Requires-Dist: ipywidgets (>=8.0.4)
Requires-Dist: pandas (>=2.2.0)
Requires-Dist: pandas-stubs (>=2.1.1.230928)
Requires-Dist: pyarrow (>=10.0.1)
Requires-Dist: python-dotenv (>=1.0.1)
Requires-Dist: requests (>=2.28.2)
Requires-Dist: toml (>=0.10.2)
Requires-Dist: types-colorama (>=0.4.15.20240205)
Requires-Dist: types-requests (>=2.31.0.10)
Requires-Dist: types-toml (>=0.10.8.7)
Project-URL: Changelog, https://github.com/statisticsnorway/dapla-statbank-client/releases
Project-URL: Documentation, https://statisticsnorway.github.io/dapla-statbank-client
Project-URL: Homepage, https://github.com/statisticsnorway/dapla-statbank-client
Project-URL: Repository, https://github.com/statisticsnorway/dapla-statbank-client
